httpout_login/__init__.py
httpout_login-0.0.0.dist-info/LICENSE
httpout_login-0.0.0.dist-info/METADATA
httpout_login-0.0.0.dist-info/WHEEL
httpout_login-0.0.0.dist-info/top_level.txt
httpout_login-0.0.0.dist-info/RECORD
